Workbook

Sheet Inicio
B9: Planificador de Patrimonio Personal
B12: Meouchi Consultores · Seguros e Inversiones
B15: ¿Estás construyendo patrimonio de verdad?
B16: Puedes ganar bien, usar tu dinero bien — y aún así no estar construyendo nada. Esta plantilla te muestra exactamente dónde estás parado y a dónde vas.
B20: 1. Mis Datos | E20: 2. Proyección
B26: → Empieza en la pestaña 'Mis Datos' → luego revisa 'Proyección'
B42: Supuestos: Inflación 4.5% anual · Rendimiento 6% anual · Modelo de renta perpetua Cálculo informativo. No constituye asesoría financiera vinculante. Regulado por la CNSF.

Sheet Mis Datos
A2: Mis Datos Financieros
A7: Perfil Personal
B9: Edad actual | C9: 35 | D9: años
B10: Edad de retiro deseada | C10: 65 | D10: años
A12: Situación Financiera Actual
B14: Ingreso mensual neto | C14: 30000 | D14: $/mes
B15: Gastos mensuales totales | C15: 25000 | D15: $/mes
B16: Lo que ahorras/inviertes hoy | C16: 4000 | D16: $/mes | E16: 🔵 Ingresa tus datos en azul
B17: Patrimonio acumulado hoy | C17: 0 | D17: $ | E17: Inversiones, ahorros, etc.
A19: Supuestos del Cálculo
B21: Inflación anual estimada | C21: 0.045 | D21: %
B22: Rendimiento anual de inversión | C22: 0.06 | D22: %
A24: Resumen Calculado
B26: Años hasta el retiro | C26: =C10-C9 -> 30
B27: Gasto mensual proyectado al retiro | C27: =C15*(1+C21)^(C10-C9) -> 93632.953
B28: Gasto anual al retiro | C28: =C27*12 -> 1123595.4
B29: Capital necesario al retiro | C29: =C28/C22 -> 18726591
B30: Brecha a cubrir | C30: =C29-C17 -> 18726591
B32: Las celdas amarillas son tus entradas. Modifícalas para simular distintos escenarios.

Sheet Proyección
A2: Proyección de Patrimonio
B7: Año | C7: Edad | D7: Trayectoria Actual ($) | E7: Con Estrategia ($) | F7: Capital Necesario ($) | G7: Diferencia ($)
B8: 0 | C8: ='Mis Datos'!C9+0 -> 35 | D8: ='Mis Datos'!C17 -> 0 | E8: ='Mis Datos'!C17 -> 0 | F8: ='Mis Datos'!C29 -> 18726591 | G8: =D8-F8 -> -18726591
B9: 1 | C9: ='Mis Datos'!C9+1 -> 36 | D9: =D8*(1+'Mis Datos'!C22)+'Mis Datos'!C16*12 -> 48000 | E9: =E8*(1+0.08)+'Mis Datos'!C16*12*1.5 -> 72000 | F9: ='Mis Datos'!C29 -> 18726591 | G9: =D9-F9 -> -18678591
B10: 2 | C10: ='Mis Datos'!C9+2 -> 37 | D10: =D9*(1+'Mis Datos'!C22)+'Mis Datos'!C16*12 -> 98880 | E10: =E9*(1+0.08)+'Mis Datos'!C16*12*1.5 -> 149760 | F10: ='Mis Datos'!C29 -> 18726591 | G10: =D10-F10 -> -18627711
B11: 3 | C11: ='Mis Datos'!C9+3 -> 38 | D11: =D10*(1+'Mis Datos'!C22)+'Mis Datos'!C16*12 -> 152812.8 | E11: =E10*(1+0.08)+'Mis Datos'!C16*12*1.5 -> 233740.8 | F11: ='Mis Datos'!C29 -> 18726591 | G11: =D11-F11 -> -18573778
B12: 4 | C12: ='Mis Datos'!C9+4 -> 39 | D12: =D11*(1+'Mis Datos'!C22)+'Mis Datos'!C16*12 -> 209981.57 | E12: =E11*(1+0.08)+'Mis Datos'!C16*12*1.5 -> 324440.06 | F12: ='Mis Datos'!C29 -> 18726591 | G12: =D12-F12 -> -18516609
B13: 5 | C13: ='Mis Datos'!C9+5 -> 40 | D13: =D12*(1+'Mis Datos'!C22)+'Mis Datos'!C16*12 -> 270580.46 | E13: =E12*(1+0.08)+'Mis Datos'!C16*12*1.5 -> 422395.27 | F13: ='Mis Datos'!C29 -> 18726591 | G13: =D13-F13 -> -18456010
B14: 6 | C14: ='Mis Datos'!C9+6 -> 41 | D14: =D13*(1+'Mis Datos'!C22)+'Mis Datos'!C16*12 -> 334815.29 | E14: =E13*(1+0.08)+'Mis Datos'!C16*12*1.5 -> 528186.89 | F14: ='Mis Datos'!C29 -> 18726591 | G14: =D14-F14 -> -18391775
B15: 7 | C15: ='Mis Datos'!C9+7 -> 42 | D15: =D14*(1+'Mis Datos'!C22)+'Mis Datos'!C16*12 -> 402904.21 | E15: =E14*(1+0.08)+'Mis Datos'!C16*12*1.5 -> 642441.84 | F15: ='Mis Datos'!C29 -> 18726591 | G15: =D15-F15 -> -18323686
B16: 8 | C16: ='Mis Datos'!C9+8 -> 43 | D16: =D15*(1+'Mis Datos'!C22)+'Mis Datos'!C16*12 -> 475078.46 | E16: =E15*(1+0.08)+'Mis Datos'!C16*12*1.5 -> 765837.19 | F16: ='Mis Datos'!C29 -> 18726591 | G16: =D16-F16 -> -18251512
B17: 9 | C17: ='Mis Datos'!C9+9 -> 44 | D17: =D16*(1+'Mis Datos'!C22)+'Mis Datos'!C16*12 -> 551583.17 | E17: =E16*(1+0.08)+'Mis Datos'!C16*12*1.5 -> 899104.16 | F17: ='Mis Datos'!C29 -> 18726591 | G17: =D17-F17 -> -18175008
B18: 10 | C18: ='Mis Datos'!C9+10 -> 45 | D18: =D17*(1+'Mis Datos'!C22)+'Mis Datos'!C16*12 -> 632678.16 | E18: =E17*(1+0.08)+'Mis Datos'!C16*12*1.5 -> 1043032.5 | F18: ='Mis Datos'!C29 -> 18726591 | G18: =D18-F18 -> -18093913
B19: 11 | C19: ='Mis Datos'!C9+11 -> 46 | D19: =D18*(1+'Mis Datos'!C22)+'Mis Datos'!C16*12 -> 718638.85 | E19: =E18*(1+0.08)+'Mis Datos'!C16*12*1.5 -> 1198475.1 | F19: ='Mis Datos'!C29 -> 18726591 | G19: =D19-F19 -> -18007952
B20: 12 | C20: ='Mis Datos'!C9+12 -> 47 | D20: =D19*(1+'Mis Datos'!C22)+'Mis Datos'!C16*12 -> 809757.18 | E20: =E19*(1+0.08)+'Mis Datos'!C16*12*1.5 -> 1366353.1 | F20: ='Mis Datos'!C29 -> 18726591 | G20: =D20-F20 -> -17916833
B21: 13 | C21: ='Mis Datos'!C9+13 -> 48 | D21: =D20*(1+'Mis Datos'!C22)+'Mis Datos'!C16*12 -> 906342.61 | E21: =E20*(1+0.08)+'Mis Datos'!C16*12*1.5 -> 1547661.4 | F21: ='Mis Datos'!C29 -> 18726591 | G21: =D21-F21 -> -17820248
B22: 14 | C22: ='Mis Datos'!C9+14 -> 49 | D22: =D21*(1+'Mis Datos'!C22)+'Mis Datos'!C16*12 -> 1008723.2 | E22: =E21*(1+0.08)+'Mis Datos'!C16*12*1.5 -> 1743474.3 | F22: ='Mis Datos'!C29 -> 18726591 | G22: =D22-F22 -> -17717868
B23: 15 | C23: ='Mis Datos'!C9+15 -> 50 | D23: =D22*(1+'Mis Datos'!C22)+'Mis Datos'!C16*12 -> 1117246.6 | E23: =E22*(1+0.08)+'Mis Datos'!C16*12*1.5 -> 1954952.2 | F23: ='Mis Datos'!C29 -> 18726591 | G23: =D23-F23 -> -17609344
B24: 16 | C24: ='Mis Datos'!C9+16 -> 51 | D24: =D23*(1+'Mis Datos'!C22)+'Mis Datos'!C16*12 -> 1232281.3 | E24: =E23*(1+0.08)+'Mis Datos'!C16*12*1.5 -> 2183348.4 | F24: ='Mis Datos'!C29 -> 18726591 | G24: =D24-F24 -> -17494309
B25: 17 | C25: ='Mis Datos'!C9+17 -> 52 | D25: =D24*(1+'Mis Datos'!C22)+'Mis Datos'!C16*12 -> 1354218.2 | E25: =E24*(1+0.08)+'Mis Datos'!C16*12*1.5 -> 2430016.2 | F25: ='Mis Datos'!C29 -> 18726591 | G25: =D25-F25 -> -17372372
B26: 18 | C26: ='Mis Datos'!C9+18 -> 53 | D26: =D25*(1+'Mis Datos'!C22)+'Mis Datos'!C16*12 -> 1483471.3 | E26: =E25*(1+0.08)+'Mis Datos'!C16*12*1.5 -> 2696417.5 | F26: ='Mis Datos'!C29 -> 18726591 | G26: =D26-F26 -> -17243119
B27: 19 | C27: ='Mis Datos'!C9+19 -> 54 | D27: =D26*(1+'Mis Datos'!C22)+'Mis Datos'!C16*12 -> 1620479.6 | E27: =E26*(1+0.08)+'Mis Datos'!C16*12*1.5 -> 2984131 | F27: ='Mis Datos'!C29 -> 18726591 | G27: =D27-F27 -> -17106111
B28: 20 | C28: ='Mis Datos'!C9+20 -> 55 | D28: =D27*(1+'Mis Datos'!C22)+'Mis Datos'!C16*12 -> 1765708.4 | E28: =E27*(1+0.08)+'Mis Datos'!C16*12*1.5 -> 3294861.4 | F28: ='Mis Datos'!C29 -> 18726591 | G28: =D28-F28 -> -16960882
B29: 21 | C29: ='Mis Datos'!C9+21 -> 56 | D29: =D28*(1+'Mis Datos'!C22)+'Mis Datos'!C16*12 -> 1919650.9 | E29: =E28*(1+0.08)+'Mis Datos'!C16*12*1.5 -> 3630450.3 | F29: ='Mis Datos'!C29 -> 18726591 | G29: =D29-F29 -> -16806940
B30: 22 | C30: ='Mis Datos'!C9+22 -> 57 | D30: =D29*(1+'Mis Datos'!C22)+'Mis Datos'!C16*12 -> 2082829.9 | E30: =E29*(1+0.08)+'Mis Datos'!C16*12*1.5 -> 3992886.4 | F30: ='Mis Datos'!C29 -> 18726591 | G30: =D30-F30 -> -16643761
B31: 23 | C31: ='Mis Datos'!C9+23 -> 58 | D31: =D30*(1+'Mis Datos'!C22)+'Mis Datos'!C16*12 -> 2255799.7 | E31: =E30*(1+0.08)+'Mis Datos'!C16*12*1.5 -> 4384317.3 | F31: ='Mis Datos'!C29 -> 18726591 | G31: =D31-F31 -> -16470791
B32: 24 | C32: ='Mis Datos'!C9+24 -> 59 | D32: =D31*(1+'Mis Datos'!C22)+'Mis Datos'!C16*12 -> 2439147.7 | E32: =E31*(1+0.08)+'Mis Datos'!C16*12*1.5 -> 4807062.7 | F32: ='Mis Datos'!C29 -> 18726591 | G32: =D32-F32 -> -16287443
B33: 25 | C33: ='Mis Datos'!C9+25 -> 60 | D33: =D32*(1+'Mis Datos'!C22)+'Mis Datos'!C16*12 -> 2633496.6 | E33: =E32*(1+0.08)+'Mis Datos'!C16*12*1.5 -> 5263627.7 | F33: ='Mis Datos'!C29 -> 18726591 | G33: =D33-F33 -> -16093094
B34: 26 | C34: ='Mis Datos'!C9+26 -> 61 | D34: =D33*(1+'Mis Datos'!C22)+'Mis Datos'!C16*12 -> 2839506.4 | E34: =E33*(1+0.08)+'Mis Datos'!C16*12*1.5 -> 5756717.9 | F34: ='Mis Datos'!C29 -> 18726591 | G34: =D34-F34 -> -15887084
B35: 27 | C35: ='Mis Datos'!C9+27 -> 62 | D35: =D34*(1+'Mis Datos'!C22)+'Mis Datos'!C16*12 -> 3057876.8 | E35: =E34*(1+0.08)+'Mis Datos'!C16*12*1.5 -> 6289255.3 | F35: ='Mis Datos'!C29 -> 18726591 | G35: =D35-F35 -> -15668714
B36: 28 | C36: ='Mis Datos'!C9+28 -> 63 | D36: =D35*(1+'Mis Datos'!C22)+'Mis Datos'!C16*12 -> 3289349.4 | E36: =E35*(1+0.08)+'Mis Datos'!C16*12*1.5 -> 6864395.7 | F36: ='Mis Datos'!C29 -> 18726591 | G36: =D36-F36 -> -15437241
B37: 29 | C37: ='Mis Datos'!C9+29 -> 64 | D37: =D36*(1+'Mis Datos'!C22)+'Mis Datos'!C16*12 -> 3534710.3 | E37: =E36*(1+0.08)+'Mis Datos'!C16*12*1.5 -> 7485547.4 | F37: ='Mis Datos'!C29 -> 18726591 | G37: =D37-F37 -> -15191880
B38: 30 | C38: ='Mis Datos'!C9+30 -> 65 | D38: =D37*(1+'Mis Datos'!C22)+'Mis Datos'!C16*12 -> 3794792.9 | E38: =E37*(1+0.08)+'Mis Datos'!C16*12*1.5 -> 8156391.2 | F38: ='Mis Datos'!C29 -> 18726591 | G38: =D38-F38 -> -14931798
B40: Gris = trayectoria actual · Naranja = con estrategia · Rojo punteado = capital necesario al retiro

Sheet Próximos Pasos
A2: Próximos Pasos
B8: 1. Define tu número mínimo de ahorro
B9: Antes de invertir, necesitas saber cuánto puedes separar cada mes de forma consistente. Ese número es tu base.
B11: 2. Automatiza antes de gastar
B12: El dinero que no ves no se gasta. Separa tu ahorro el mismo día que entra tu ingreso — antes de cualquier gasto.
B14: 3. Entiende la diferencia entre ahorrar e invertir
B15: Ahorrar preserva valor. Invertir lo multiplica. Un fondo de retiro bien estructurado hace las dos cosas a la vez.
B17: 4. Habla con un asesor cuando estés listo
B18: Cuando alcances $4,000/mes de ahorro sostenido, ese es el momento de poner ese dinero a trabajar en serio con un plan.
B20: 5. El tiempo es tu activo más valioso
B21: Empezar hoy con poco supera casi siempre a empezar mañana con mucho. El interés compuesto trabaja con quien empieza antes.
B24: ¿Lista para construir tu patrimonio? → wa.me/528140078720
